numprioricog/__init__.py
numprioricog-1.0.dist-info/LICENSE
numprioricog-1.0.dist-info/METADATA
numprioricog-1.0.dist-info/WHEEL
numprioricog-1.0.dist-info/top_level.txt
numprioricog-1.0.dist-info/RECORD
