Metadata-Version: 2.1
Name: numprioricog
Version: 1.0
Summary: Un aplicació para comprobar si un número es primo.
Home-page: UNKNOWN
Author: Oscar Rico
Author-email: oricog@gmail.com
License: GNU GPLv3
Keywords: primenumber mathematical operations
Platform: UNKNOWN
Classifier: Development Status :: 4 - Beta
Classifier: Intended Audience :: Developers
Classifier: Topic :: Utilities
Classifier: License :: OSI Approved :: GNU General Public License v3 (GPLv3)
Classifier: Programming Language :: Python :: 3
Classifier: Operating System :: OS Independent
